climate_ref_esmvaltool/__init__.py
climate_ref_esmvaltool/_version.py
climate_ref_esmvaltool/py.typed
climate_ref_esmvaltool/recipe.py
climate_ref_esmvaltool/recipes.txt
climate_ref_esmvaltool/types.py
climate_ref_esmvaltool/dataset_registry/data.txt
climate_ref_esmvaltool/diagnostics/__init__.py
climate_ref_esmvaltool/diagnostics/base.py
climate_ref_esmvaltool/diagnostics/climate_at_global_warming_levels.py
climate_ref_esmvaltool/diagnostics/climate_drivers_for_fire.py
climate_ref_esmvaltool/diagnostics/cloud_radiative_effects.py
climate_ref_esmvaltool/diagnostics/cloud_scatterplots.py
climate_ref_esmvaltool/diagnostics/ecs.py
climate_ref_esmvaltool/diagnostics/enso.py
climate_ref_esmvaltool/diagnostics/example.py
climate_ref_esmvaltool/diagnostics/regional_historical_changes.py
climate_ref_esmvaltool/diagnostics/sea_ice_area_basic.py
climate_ref_esmvaltool/diagnostics/sea_ice_sensitivity.py
climate_ref_esmvaltool/diagnostics/tcr.py
climate_ref_esmvaltool/diagnostics/tcre.py
climate_ref_esmvaltool/diagnostics/zec.py
climate_ref_esmvaltool/requirements/conda-lock.yml
climate_ref_esmvaltool/requirements/environment.yml
climate_ref_esmvaltool-0.8.1.dist-info/METADATA
climate_ref_esmvaltool-0.8.1.dist-info/WHEEL
climate_ref_esmvaltool-0.8.1.dist-info/entry_points.txt
climate_ref_esmvaltool-0.8.1.dist-info/licenses/LICENCE
climate_ref_esmvaltool-0.8.1.dist-info/licenses/NOTICE
climate_ref_esmvaltool-0.8.1.dist-info/RECORD
